{
  "project_info": {
    "project_number": "143187285230",
    "project_id": "mine-track-23a18",
    "storage_bucket": "mine-track-23a18.appspot.com"
  },
  "client": [
    {
      "client_info": {
        "mobilesdk_app_id": "1:143187285230:android:c9294212501f69efc24fff",
        "android_client_info": {
          "package_name": "com.shiftlink.app"
        }
      },
      "oauth_client": [],
      "api_key": [
        {
          "current_key": "AIzaSyDxvxUBK4Yuhm6unSGGLcFDEWPZa629W1c"
        }
      ],
      "services": {
        "appinvite_service": {
          "other_platform_oauth_client": []
        }
      }
    }
  ],
  "configuration_version": "1"
}